Metadata-Version: 2.1
Name: cryptostocks
Version: 0.2.3
Summary: Get current price of crypto from most popular stock exchanges
Home-page: UNKNOWN
License: UNKNOWN
Platform: UNKNOWN
